pths/__init__.py
pths-0.1.15.dist-info/LICENSE
pths-0.1.15.dist-info/METADATA
pths-0.1.15.dist-info/WHEEL
pths-0.1.15.dist-info/top_level.txt
pths-0.1.15.dist-info/RECORD
