Metadata-Version: 2.1
Name: pths
Version: 0.1.15
Summary: pth install class
License: MIT
Requires-Python: >=3.9
License-File: LICENSE
Requires-Dist: loguru <1,>=0.7.2
Requires-Dist: loguru-config <1,>=0.1.0
Requires-Dist: setuptools <69,>=68.2.2
Provides-Extra: dev
Requires-Dist: black ; extra == 'dev'
Requires-Dist: icecream ; extra == 'dev'
Requires-Dist: ipython ; extra == 'dev'
Requires-Dist: ipython-suggestions ; extra == 'dev'
Requires-Dist: restmagic ; extra == 'dev'
Requires-Dist: mypy ; extra == 'dev'
Requires-Dist: pip-tools ; extra == 'dev'
Requires-Dist: pyflyby ; extra == 'dev'
Requires-Dist: python-semantic-release ; extra == 'dev'
Requires-Dist: ruff ; extra == 'dev'
Requires-Dist: ruff-lsp ; extra == 'dev'
Requires-Dist: twine ; extra == 'dev'
Requires-Dist: vendorize ; extra == 'dev'
Provides-Extra: docs
Requires-Dist: docutils ; extra == 'docs'
Requires-Dist: sphinx ; extra == 'docs'
Requires-Dist: sphinx-click ; extra == 'docs'
Requires-Dist: sphinx-rtd-theme ; extra == 'docs'
Requires-Dist: sphinxcontrib-napoleon ; extra == 'docs'
Provides-Extra: tests
Requires-Dist: coverage[toml] <7,>=6 ; extra == 'tests'
Requires-Dist: darglint <2,>=1.8.1 ; extra == 'tests'
Requires-Dist: environs <10,>=9.5.0 ; extra == 'tests'
Requires-Dist: pydocstyle <7,>=6.3 ; extra == 'tests'
Requires-Dist: pytest <8,>=7 ; extra == 'tests'
Requires-Dist: pytest-asyncio <1,>=0.21.1 ; extra == 'tests'
Requires-Dist: pytest-cov <5,>=4 ; extra == 'tests'
Requires-Dist: pytest-doctestplus <1,>=0.13 ; extra == 'tests'
Requires-Dist: pytest-github-actions-annotate-failures ; extra == 'tests'
Requires-Dist: pytest-loguru <1,>=0.2.0 ; extra == 'tests'
Requires-Dist: pytest-mock <4,>=3 ; extra == 'tests'
Requires-Dist: pytest-xdist <3,>=2 ; extra == 'tests'
Requires-Dist: pytest-remotedata <1,>=0.4.0 ; extra == 'tests'
Requires-Dist: pytest-lazy-fixture ~=0.6.3 ; extra == 'tests'
Requires-Dist: pytest-sugar <1,>=0.9.7 ; extra == 'tests'
Requires-Dist: responses ==0.21.0 ; extra == 'tests'
Requires-Dist: requests-mock <2,>=1.10.0 ; extra == 'tests'
Requires-Dist: ruff <0.1,>=0.0.282 ; extra == 'tests'
Requires-Dist: tox <5,>=4.6.4 ; extra == 'tests'
Requires-Dist: types-pytest-lazy-fixture >=0.6.3.3 ; extra == 'tests'
